setup.py
src/exceptional/__init__.py
src/exceptional_python.egg-info/PKG-INFO
src/exceptional_python.egg-info/SOURCES.txt
src/exceptional_python.egg-info/dependency_links.txt
src/exceptional_python.egg-info/top_level.txt