Metadata-Version: 1.0
Name: exceptional-python
Version: 0.2.1
Summary: A python client for Exceptional (getexceptional.com), ported from pylons-exceptional
Home-page: https://github.com/cenkalti/exceptional-python
Author: Cenk Alti
Author-email: cenkalti@gmail.com
License: UNKNOWN
Platform: UNKNOWN
